sinetstreamplugin/valuetype/image.py
sinetstream_type_image-1.9.2.dist-info/METADATA
sinetstream_type_image-1.9.2.dist-info/WHEEL
sinetstream_type_image-1.9.2.dist-info/entry_points.txt
sinetstream_type_image-1.9.2.dist-info/RECORD
