Metadata-Version: 2.4
Name: sinetstream-type-image
Version: 1.9.2
Summary: Image Type plugin for SINETStream library
Project-URL: Documentation, https://www.sinetstream.net/
Project-URL: Repository, https://github.com/nii-gakunin-cloud/sinetstream.git
License: Apache License, Version 2.0
Classifier: Intended Audience :: Developers
Classifier: License :: OSI Approved :: Apache Software License
Classifier: Programming Language :: Python :: 3 :: Only
Classifier: Topic :: Software Development :: Libraries :: Python Modules
Requires-Python: >=3.9
Requires-Dist: numpy; python_version >= '3.9'
Requires-Dist: numpy<1.22.0; python_version < '3.8'
Requires-Dist: numpy<1.25.0,>=1.22.0; python_version >= '3.8' and python_version < '3.9'
Requires-Dist: opencv-python
Requires-Dist: sinetstream>=1.8.1; python_version < '3.12'
Requires-Dist: sinetstream>=1.8.2; python_version >= '3.12'
